nerva_sympy/__init__.py
nerva_sympy/activation_functions.py
nerva_sympy/layers.py
nerva_sympy/loss_functions.py
nerva_sympy/matrix_operations.py
nerva_sympy/optimizers.py
nerva_sympy/softmax_functions.py
nerva_sympy/utilities.py
nerva_sympy/weight_initializers.py
nerva_sympy-0.22.0.dist-info/licenses/LICENSE
nerva_sympy-0.22.0.dist-info/METADATA
nerva_sympy-0.22.0.dist-info/WHEEL
nerva_sympy-0.22.0.dist-info/top_level.txt
nerva_sympy-0.22.0.dist-info/RECORD
