Metadata-Version: 2.4
Name: nerva-sympy
Version: 0.22.0
Summary: Validation of neural network equations in SymPy.
Home-page: https://github.com/wiegerw/nerva-sympy
Author: Wieger Wesselink
Author-email: j.w.wesselink@tue.nl
Project-URL: Bug Tracker, https://github.com/wiegerw/nerva-sympy/issues
Classifier: Programming Language :: Python :: 3
Classifier: License :: OSI Approved :: Boost Software License 1.0 (BSL-1.0)
Classifier: Operating System :: OS Independent
Requires-Python: >=3.10
License-File: LICENSE
Requires-Dist: numpy>=1.21
Requires-Dist: sympy>=1.9
Requires-Dist: scikit-learn>=1.1
Requires-Dist: nerva-jax>=0.4
Requires-Dist: nerva-numpy>=0.4
Requires-Dist: nerva-tensorflow>=0.4
Requires-Dist: nerva-torch>=0.4
Dynamic: license-file
